{
  "id": 1019771611,
  "title": "Euphonic Sessions with Kyau & Albert - April 2021 Edition",
  "description": "01 M.O.S. - Paenoia [Anjunadeep]\n02 Bands - Supernova [Armada]\n03 Le Youth - Underwater  (thomfjord Remix) [Armada] [TRACK OF THE MONTH]\n04 Chicane - Don't Look Down [Modena]\n05 Beatsole - MIR (Maywave Remix) [Euphonic]\n06 Sohmi - Closer [Odd One Out]\n07 CRi ft. Bernache - From Me (Icarus Remix) [Anjunadeep]\n08 Binary Finary - 1998 (Jose De Mara Remix) [Armind]\n09 Adam Sobiech - Daylight [Euphonic]\n10 Genix - Dance It Out [Anjunabeats]\n11 Ahmed Helmy - Progressor [AVA]\n12 Merisem - Golden Waves [Redux Deep]\n13 Dan Stone - Back To You (Koyah Remix) [Elliptical Sun]\n14 ilan Bluestone ft. Ellen Smith - Stranger To Your Love [Anjunabeats]\n15 Ferry Corsten & Ruben de Ronde - Bloodstream [Flashover]\n16 Sam Heyman - Corvus [Scorchin' Progressive]\n17 Fluente - Miasma [Euphonic Visions]\n18 Tomas Heredia - Gave U My Love (Mike Saint-Jules Remix) [Anjunabeats]\n19 Duran & Aytek - Raindrops [Perfecto]\n20 Solarstone - Solarcoaster (Marsh Remix) [Armada]\n21 AVIRA - Late Delivery [Armada]\n22 Dezza & Lewyn - Won t Let Go [Colorize]\n23 Nomra & MØØNE - Fall In [Enhanced]\n24 Eran Hersh & May Kravitz - Human (Passenger 10 Remix) [Sirup Music]\n25 Kryder & Mark Roma - Pleasure Or Pain [Black Hole]\n26 GVN - Ethereal [Anjunabeats]\n27 Vintage & Morelli x Monoverse - Maverick [Monstercat Silk]\n28 Dennis Sheperd - Miss You [Black Hole]",
  "permalink_url": "https://soundcloud.com/euphonicsessions/euphonic-sessions-april2021",
  "duration": 7273241,
  "playback_count": 8763,
  "likes_count": 326,
  "comment_count": 23,
  "created_at": "2021-03-31T15:01:14Z",
  "genre": "",
  "tag_list": "\"EuphonicSessions \"",
  "artwork_url": "https://i1.sndcdn.com/artworks-YOSpxQxvCZk0gLY5-15kqeg-large.jpg"
}